Workbook

Sheet DashBoard
C3: AUDI GROUP - FINANCIAL MODEL DASHBOARD
C4: Forecast 2025–2027 | Scenarios: Base / Bull / Bear
C6: Active Scenario → | D6: =Drivers!G1 -> Bull
C12: ='IS Forecast'!G2 -> 76851.804 | E12: ='IS Forecast'!G8 -> 8453.6985 | F12: =DCF!G8 -> 12937.032 | H12: =DCF!G14 -> 246160.26
H37: Metric | I37: Base | J37: Bull | K37: Bear
H38: Revenue 2027F | I38: ='IS Forecast'!G2 -> 76851.804 | J38: ='IS Forecast'!G2*(1+Drivers!G5) -> 78388.84 | K38: ='IS Forecast'!G2*(1+Drivers!G6) -> 75314.768
H39: EBIT 2027F | I39: ='IS Forecast'!G8 -> 8453.6985 | J39: ='IS Forecast'!G8*(1+Drivers!G5-Drivers!I5) -> 8538.2354 | K39: ='IS Forecast'!G8*(1+Drivers!G6-Drivers!I6) -> 8369.1615
H40: FCF 2027F | I40: ='CF Forecast'!G8 -> 9137.704 | J40: ='CF Forecast'!G8*(1+Drivers!G5-Drivers!I5) -> 9229.081 | K40: ='CF Forecast'!G8*(1+Drivers!G6-Drivers!I6) -> 9046.3269
H41: Enterprise Value | I41: =DCF!G14 -> 246160.26 | J41: =DCF!G14*(1+Drivers!G5-Drivers!H5) -> 253545.07 | K41: =DCF!G14*(1+Drivers!G6-Drivers!H6) -> 238775.45

Sheet Drivers
A1: Driver | B1: 2025F | C1: 2026F | D1: 2027F | F1: Scenario | G1: Bull
A2: Revenue growth % | B2: =0.05 + $G$8 -> 0.07 | C2: =0.04 + $G$8 -> 0.06 | D2: =0.03 + $G$8 -> 0.05
A3: COGS % of revenue | B3: =-0.84 + $I$8 -> -0.83 | C3: =-0.83 + $I$8 -> -0.82 | D3: =-0.82 + $I$8 -> -0.81 | F3: Scenario | G3: RevAdj | H3: WACCAdj | I3: COGSAdj
A4: Distribution % of revenue | B4: -0.05 | C4: -0.05 | D4: -0.05 | F4: Base | G4: 0 | H4: 0 | I4: 0
A5: Admin % of revenue | B5: -0.01 | C5: -0.01 | D5: -0.01 | F5: Bull | G5: 0.02 | H5: -0.01 | I5: 0.01
A6: Other op result % | B6: -0.03 | C6: -0.03 | D6: -0.02 | F6: Bear | G6: -0.02 | H6: 0.01 | I6: -0.01
A7: Tax rate | B7: 0.26 | C7: 0.26 | D7: 0.26
A8: CapEx % of revenue | B8: 0.06 | C8: 0.06 | D8: 0.06 | G8: =INDEX($G$4:$G$6, MATCH($G$1, $F$4:$F$6, 0)) -> 0.02 | H8: =INDEX($H$4:$H$6, MATCH($G$1, $F$4:$F$6, 0)) -> -0.01 | I8: =INDEX($I$4:$I$6, MATCH($G$1, $F$4:$F$6, 0)) -> 0.01
A9: D&A % of revenue | B9: 0.04 | C9: 0.04 | D9: 0.04
A10: Inventory % of revenue | B10: 0.12 | C10: 0.12 | D10: 0.12
A11: Receivables % of revenue | B11: 0.09 | C11: 0.09 | D11: 0.09
A12: Payables % of COGS | B12: 0.16 | C12: 0.16 | D12: 0.16
A13: WACC | B13: =0.08 + $H$8 -> 0.07 | C13: =B13 -> 0.07 | D13: =B13 -> 0.07
A14: Terminal growth | D14: 0.02

Sheet IS Forecast
A1: Income Statement Forecast | B1: 2024 | C1: 2023 | D1: 2022 | E1: 2025F | F1: 2026F | G1: 2027F
A2: Revenue | B2: 64532 | C2: 69865 | D2: 61753 | E2: =B2 * (1 + Drivers!B2) -> 69049.24 | F2: =E2 * (1 + Drivers!C2) -> 73192.194 | G2: =F2 * (1 + Drivers!D2) -> 76851.804
A3: Cost of goods sold | B3: -54419 | C3: -58576 | D3: -52237 | E3: =E2 * Drivers!B3 -> -57310.869 | F3: =F2 * Drivers!C3 -> -60017.599 | G3: =G2 * Drivers!D3 -> -62249.961
A4: Gross profit from sales | B4: 10113 | C4: 11289 | D4: 9516 | E4: =E2 + E3 -> 11738.371 | F4: =F2 + F3 -> 13174.595 | G4: =G2 + G3 -> 14601.843
A5: Distribution expenses | B5: -3352 | C5: -3377 | D5: -3184 | E5: =E2 * Drivers!B4 -> -3452.462 | F5: =F2 * Drivers!C4 -> -3659.6097 | G5: =G2 * Drivers!D4 -> -3842.5902
A6: Administrative expenses | B6: -762 | C6: -771 | D6: -759 | E6: =E2 * Drivers!B5 -> -690.4924 | F6: =F2 * Drivers!C5 -> -731.92194 | G6: =G2 * Drivers!D5 -> -768.51804
A7: Other operating result | B7: -2123 | C7: -860 | D7: 1977 | E7: =E2 * Drivers!B6 -> -2071.4772 | F7: =F2 * Drivers!C6 -> -2195.7658 | G7: =G2 * Drivers!D6 -> -1537.0361
A8: EBIT | B8: 3903 | C8: 6280 | D8: 7550 | E8: =E4 + E5 + E6 + E7 -> 5523.9392 | F8: =F4 + F5 + F6 + F7 -> 6587.2975 | G8: =G4 + G5 + G6 + G7 -> 8453.6985
A9: Financial result | B9: 1097 | C9: 1423 | D9: 1522 | E9: =$B$9 -> 1097 | F9: =$B$9 -> 1097 | G9: =$B$9 -> 1097
A10: Profit before tax | B10: 5000 | C10: 7703 | D10: 9072 | E10: =E8 + E9 -> 6620.9392 | F10: =F8 + F9 -> 7684.2975 | G10: =G8 + G9 -> 9550.6985
A11: Income tax expense | B11: -811 | C11: -1443 | D11: -1956 | E11: =E10 *-Drivers!B7 -> -1721.4442 | F11: =F10 *-Drivers!C7 -> -1997.9173 | G11: =G10 *-Drivers!D7 -> -2483.1816
A12: Profit after tax | B12: 4189 | C12: 6260 | D12: 7116 | E12: =E10 + E11 -> 4899.495 | F12: =F10 + F11 -> 5686.3801 | G12: =G10 + G11 -> 7067.5169

Sheet BS Forecast
A1: Balance Sheet | B1: 2024 | C1: 2023 | D1: 2022 | E1: 2025F | F1: 2026F | G1: 2027F
A2: Non-current assets | B2: 35318 | C2: 35230 | D2: 32675 | E2: =B2 + ('IS Forecast'!E2 * Drivers!B8) - ('IS Forecast'!E2 * Drivers!B9) -> 36698.985 | F2: =E2 + ('IS Forecast'!F2 * Drivers!C8) - ('IS Forecast'!F2 * Drivers!C9) -> 38162.829 | G2: =F2 + ('IS Forecast'!G2 * Drivers!D8) - ('IS Forecast'!G2 * Drivers!D9) -> 39699.865
A3: Current assets | B3: 37703 | C3: 38199 | D3: 38119 | E3: =E4+E5+E6+E7 -> 30487.249 | F3: =F4+F5+F6+F7 -> 34537.261 | G3: =G4+G5+G6+G7 -> 39832.375
A4: of which inventories | B4: 7837 | C4: 7966 | D4: 8336 | E4: ='IS Forecast'!E2 * Drivers!B10 -> 8285.9088 | F4: ='IS Forecast'!F2 * Drivers!C10 -> 8783.0633 | G4: ='IS Forecast'!G2 * Drivers!D10 -> 9222.2165
A5: of which trade receivables | B5: 5932 | C5: 5598 | D5: 5471 | E5: ='IS Forecast'!E2 * Drivers!B11 -> 6214.4316 | F5: ='IS Forecast'!F2 * Drivers!C11 -> 6587.2975 | G5: ='IS Forecast'!G2 * Drivers!D11 -> 6916.6624
A6: of which cash and cash equivalents | B6: 12229 | C6: 13436 | D6: 9599 | E6: ='CF Forecast'!E14 -> 15910.909 | F6: ='CF Forecast'!F14 -> 19090.9 | G6: ='CF Forecast'!G14 -> 23617.496
A7: Assets held for sale | B7: 76 | C7: 18 | D7: 18 | E7: =$B$7 -> 76 | F7: =$B$7 -> 76 | G7: =$B$7 -> 76
A8: Total assets | B8: 73097 | C8: 73447 | D8: 70812 | E8: =E2+E3 -> 67186.234 | F8: =F2+F3 -> 72700.09 | G8: =G2+G3 -> 79532.24
A10: Equity | B10: 35882 | C10: 33839 | D10: 31582 | E10: =B10 + 'IS Forecast'!E12 -> 40781.495 | F10: =E10 + 'IS Forecast'!F12 -> 46467.875 | G10: =F10 + 'IS Forecast'!G12 -> 53535.392
A12: Liabilities | B12: 37215 | C12: 39608 | D12: 39230 | E12: =E13+E14 -> 38160.739 | F12: =F13+F14 -> 38593.816 | G12: =G13+G14 -> 38950.994
A13: of which non-current liabilities | B13: 14882 | C13: 15228 | D13: 14415 | E13: =$B$13 -> 14882 | F13: =$B$13 -> 14882 | G13: =$B$13 -> 14882
A14: of which current liabilities | B14: 22384 | C14: 24380 | D14: 24815 | E14: =E15+14109 -> 23278.739 | F14: =F15+14109 -> 23711.816 | G14: =G15+14109 -> 24068.994
A15: of which trade payables | B15: 8275 | C15: 8839 | D15: 8632 | E15: =ABS( 'IS Forecast'!E3 * Drivers!B12) -> 9169.7391 | F15: =ABS( 'IS Forecast'!F3 * Drivers!C12) -> 9602.8159 | G15: =ABS( 'IS Forecast'!G3 * Drivers!D12) -> 9959.9938
A16: Balancing item (temporary) | E16: =E8-(E10+E12) -> -11756 | F16: =F8-(F10+F12) -> -12361.601 | G16: =G8-(G10+G12) -> -12954.146
A17: Total equity and liabilities | B17: 73097 | C17: 73447 | D17: 70812 | E17: =E10+E12+E16 -> 67186.234 | F17: =F10+F12+F16 -> 72700.09 | G17: =G10+G12+G16 -> 79532.24

Sheet CF Forecast
A1: Cash Flow Statement Forecast | E1: 2025F | F1: 2026F | G1: 2027F
A2: Net income | E2: ='IS Forecast'!E12 -> 4899.495 | F2: ='IS Forecast'!F12 -> 5686.3801 | G2: ='IS Forecast'!G12 -> 7067.5169
A3: Depreciation & amortization | E3: ='IS Forecast'!E2 * Drivers!B9 -> 2761.9696 | F3: ='IS Forecast'!F2 * Drivers!C9 -> 2927.6878 | G3: ='IS Forecast'!G2 * Drivers!D9 -> 3074.0722
A4: Change in inventories | E4: ='BS Forecast'!E4 - 'BS Forecast'!B4 -> 448.9088 | F4: ='BS Forecast'!F4 - 'BS Forecast'!C4 -> 817.06333 | G4: ='BS Forecast'!G4 - 'BS Forecast'!D4 -> 886.21649
A5: Change in receivables | E5: ='BS Forecast'!E5 - 'BS Forecast'!B5 -> 282.4316 | F5: ='BS Forecast'!F5 - 'BS Forecast'!C5 -> 989.2975 | G5: ='BS Forecast'!G5 - 'BS Forecast'!D5 -> 1445.6624
A6: Change in payables | E6: ='BS Forecast'!E15 - 'BS Forecast'!B15 -> 894.73907 | F6: ='BS Forecast'!F15 - 'BS Forecast'!C15 -> 763.81591 | G6: ='BS Forecast'!G15 - 'BS Forecast'!D15 -> 1327.9938
A7: Change in working capital | E7: =E4 + E5 - E6 -> -163.39867 | F7: =F4 + F5 - F6 -> 1042.5449 | G7: =G4 + G5 - G6 -> 1003.8851
A8: Cash flow from operations | E8: =E2 + E3 - E7 -> 7824.8633 | F8: =F2 + F3 - F7 -> 7571.523 | G8: =G2 + G3 - G7 -> 9137.704
A9: Capital expenditures (CapEx) | E9: ='IS Forecast'!E2 * -Drivers!B8 -> -4142.9544 | F9: ='IS Forecast'!F2 * -Drivers!C8 -> -4391.5317 | G9: ='IS Forecast'!G2 * -Drivers!D8 -> -4611.1082
A10: Cash flow from investing | E10: =E9 -> -4142.9544 | F10: =F9 -> -4391.5317 | G10: =G9 -> -4611.1082
A11: Cash flow from financing | E11: =0 -> 0 | F11: =0 -> 0 | G11: =0 -> 0
A12: Net change in cash | E12: =E8 + E10 + E11 -> 3681.9089 | F12: =F8 + F10 + F11 -> 3179.9913 | G12: =G8 + G10 + G11 -> 4526.5957
A13: Beginning cash | E13: ='BS Forecast'!B6 -> 12229 | F13: =E14 -> 15910.909 | G13: =F14 -> 19090.9
A14: Ending cash | E14: =E13 + E12 -> 15910.909 | F14: =F13 + F12 -> 19090.9 | G14: =G13 + G12 -> 23617.496

Sheet DCF
A1: Free Cash Flow Forecast | E1: 2025F | F1: 2026F | G1: 2027F
A2: EBIT | E2: ='IS Forecast'!E8 -> 5523.9392 | F2: ='IS Forecast'!F8 -> 6587.2975 | G2: ='IS Forecast'!G8 -> 8453.6985
A3: Tax on EBIT | E3: =-E2 * Drivers!B7 -> -1436.2242 | F3: =-F2 * Drivers!C7 -> -1712.6973 | G3: =-G2 * Drivers!D7 -> -2197.9616
A4: NOPAT | E4: =E2+E3 -> 4087.715 | F4: =F2+F3 -> 4874.6001 | G4: =G2+G3 -> 6255.7369
A5: Depreciation & amortization | E5: ='IS Forecast'!E2 * Drivers!B9 -> 2761.9696 | F5: ='IS Forecast'!F2 * Drivers!C9 -> 2927.6878 | G5: ='IS Forecast'!G2 * Drivers!D9 -> 3074.0722
A6: Change in working capital | E6: ='CF Forecast'!E7 -> -163.39867 | F6: ='CF Forecast'!F7 -> 1042.5449 | G6: ='CF Forecast'!G7 -> 1003.8851
A7: Capital expenditures (CapEx) | E7: ='IS Forecast'!E2 * -Drivers!B8 -> -4142.9544 | F7: ='IS Forecast'!F2 * -Drivers!C8 -> -4391.5317 | G7: ='IS Forecast'!G2 * -Drivers!D8 -> -4611.1082
A8: Free cash flow (unlevered) | E8: =E4 + E5 - E6 - E7 -> 11156.038 | F8: =F4 + F5 - F6 - F7 -> 11151.275 | G8: =G4 + G5 - G6 - G7 -> 12937.032
A9: Discount factor | E9: =1 / (1 + Drivers!$D$13) -> 0.93457944 | F9: =1 / (1 + Drivers!$D$13)^2 -> 0.87343873 | G9: =1 / (1 + Drivers!$D$13)^3 -> 0.81629788
A10: Present value of FCF | E10: =E8 * E9 -> 10426.203 | F10: =F8 * F9 -> 9739.9552 | G10: =G8 * G9 -> 10560.472
A12: Terminal value (at end of 2027) | G12: =G8 * (1 + Drivers!D14) / (Drivers!D13 - Drivers!D14) -> 263915.46
A13: PV of terminal value | G13: =G12 * G9 -> 215433.63
A14: Enterprise value | G14: =SUM(E10:G10) + G13 -> 246160.26

Sheet IS Actuals
A1: Income Statement | B1: 2024 | C1: 2023 | D1: 2022
A2: Revenue | B2: 64532 | C2: 69865 | D2: 61753
A3: Cost of goods sold | B3: -54419 | C3: -58576 | D3: -52237
A4: Gross profit from sales | B4: 10113 | C4: 11289 | D4: 9516
A5: Distribution expenses | B5: -3352 | C5: -3377 | D5: -3184
A6: Administrative expenses | B6: -762 | C6: -771 | D6: -759
A7: Other operating result | B7: -2123 | C7: -860 | D7: 1977
A8: Operating profit | B8: 3903 | C8: 6280 | D8: 7550
A9: ROS (return on sales) in % | B9: 0.06 | C9: 0.09 | D9: 0.122
A10: Financial result | B10: 1097 | C10: 1423 | D10: 1522
A11: Profit before tax | B11: 5000 | C11: 7703 | D11: 9072
A12: Income tax expense | B12: -811 | C12: -1443 | D12: -1956
A13: Profit after tax | B13: 4189 | C13: 6260 | D13: 7116

Sheet BS Actuals
A1: Balance Sheet | B1: 2024 | C1: 2023 | D1: 2022
A2: Non-current assets | B2: 35318 | C2: 35230 | D2: 32675
A3: Current assets | B3: 37703 | C3: 38199 | D3: 38119
A4: of which inventories | B4: 7837 | C4: 7966 | D4: 8336
A5: of which trade receivables | B5: 5932 | C5: 5598 | D5: 5471
A6: of which cash and cash equivalents | B6: 12229 | C6: 13436 | D6: 9599
A7: Assets held for sale | B7: 76 | C7: 18 | D7: 18
A8: Total assets | B8: 73097 | C8: 73447 | D8: 70812
A10: Equity | B10: 35882 | C10: 33839 | D10: 31582
A12: Liabilities | B12: 37215 | C12: 39608 | D12: 39230
A13: of which non-current liabilities | B13: 14882 | C13: 15228 | D13: 14415
A14: of which current liabilities | B14: 22384 | C14: 24380 | D14: 24815
... A17: Total equity and liabilities | B17: 73097 | C17: 73447 | D17: 70812

Sheet CF Actuals
A1: Cash Flow Statement | B1: 2024 | C1: 2023 | D1: 2022
A2: Cash and cash equivalents as of January 1 | B2: 13436 | C2: 9599 | D2: 12235
A4: Cash flow from operating activities | B4: 8674 | C4: 11135 | D4: 10028
A6: Investing activities attributable to operating activities | B6: -5602 | C6: -6395 | D6: -5221
A7: of which capital expenditure | B7: -3487 | C7: -3251 | D7: -2590
A8: of which additions to capitalized development costs | B8: -2141 | C8: -2705 | D8: -2079
A9: of which change in participations | B9: -22 | C9: -504 | D9: -697
A10: of which disposal of fixed assets | B10: 48 | C10: 64 | D10: 145
A12: Net cash flow | B12: 3072 | C12: 4740 | D12: 4808
A14: Change in cash deposits and loans extended | B14: -392 | C14: 3596 | D14: -3148
A15: Capital contributions from non-controlling interests | B15: 0 | C15: 0 | D15: 191
A16: Profit transfer to the Volkswagen Group | B16: -3831 | C16: -3546 | D16: -4025
... A27: Cash flow from financing activities | B27: -4099 | C27: -4312 | D27: -4327
